{
  "product_id": "prod1766150447922357",
  "product_info": {
    "name": "Modern Modern 69",
    "status": "published",
    "description": "A beautiful 22k Gold modern. Perfect for any occasion.",
    "category": "Bangles",
    "subcategory": "Modern",
    "collections": [
      "Festive Glow"
    ],
    "base_price": 16929,
    "compare_at_price": 18804,
    "general_size_info": "Standard sizing available"
  },
  "media_groups": {
    "default": {
      "images": [
        {
          "url": "https://cdn.jsdelivr.net/gh/salma-R-786/Product_Mock/products/prod1766150447922357/images/default/01.webp",
          "name": "Front View"
        }
      ],
      "instagram": []
    }
  },
  "variant_setup": {
    "has_variants": false,
    "option_definitions": []
  },
  "details": [
    {
      "label": "Material",
      "content": "22k Gold"
    },
    {
      "label": "Weight",
      "content": "8g"
    }
  ]
}